world4py/__init__.py
world4py/helper.py
world4py/libworld.dylib
world4py/logger.py
world4py/native/__init__.py
world4py/native/apidefinitions.py
world4py/native/apis.py
world4py/native/instance.py
world4py/native/structures.py
world4py/native/tools.py
world4py/native/toolsdefinitions.py
world4py/native/utils.py
world4py/np/__init__.py
world4py/np/apidefinitions.py
world4py/np/apis.py
world4py/np/instance.py
world4py/np/structures.py
world4py/np/tools.py
world4py/np/toolsdefinitions.py
world4py/np/utils.py
world4py-0.1.dist-info/METADATA
world4py-0.1.dist-info/WHEEL
world4py-0.1.dist-info/top_level.txt
world4py-0.1.dist-info/RECORD
